symbologyl2-0.1.6.dist-info/METADATA
symbologyl2-0.1.6.dist-info/WHEEL
symbologyl2-0.1.6.dist-info/licenses/LICENSE.txt
symbologyl2/__init__.py
symbologyl2/_native.cpython-38-x86_64-linux-gnu.so
symbologyl2/_native.pyi
symbologyl2/lib.py
symbologyl2-0.1.6.dist-info/RECORD
