Metadata-Version: 2.4
Name: symbologyl2
Version: 0.1.6
Classifier: License :: OSI Approved :: MIT License
Classifier: Programming Language :: Rust
Classifier: Programming Language :: Python :: Implementation :: PyPy
Classifier: Programming Language :: Python :: 3.10
Classifier: Programming Language :: Python :: 3.11
Classifier: Programming Language :: Python :: 3.12
Classifier: Programming Language :: Python :: 3.13
Classifier: Programming Language :: Python :: Implementation :: CPython
Classifier: Operating System :: OS Independent
License-File: LICENSE.txt
Summary: A python wrapper for symbologyl2 (https://github.com/onechronos/symbologyl2)
Author-email: OneChronos Engineering <engineering@onechronos.com>
License: MIT
Requires-Python: >=3.10, <4.0
Project-URL: Homepage, https://github.com/onechronos/symbologyl2-py
Project-URL: Documentation, https://symbologyl2-py.readthedocs.io/en/latest/index.html
Project-URL: Source, https://github.com/onechronos/symbologyl2-py
Project-URL: homepage, https://github.com/onechronos/symbologyl2-py
Project-URL: repository, https://github.com/onechronos/symbologyl2-py
Project-URL: documentation, https://symbologyl2-py.readthedocs.io/en/latest/index.html
